trytond/modules/authentication_totp/__init__.py
trytond/modules/authentication_totp/exception.py
trytond/modules/authentication_totp/ir.py
trytond/modules/authentication_totp/ir.xml
trytond/modules/authentication_totp/message.xml
trytond/modules/authentication_totp/res.py
trytond/modules/authentication_totp/res.xml
trytond/modules/authentication_totp/tryton.cfg
trytond/modules/authentication_totp/icons/tryton-totp-key.svg
trytond/modules/authentication_totp/tests/__init__.py
trytond/modules/authentication_totp/tests/test_authentication_totp.py
trytond/modules/authentication_totp/view/user_form.xml
trytond/modules/authentication_totp/view/user_form_preferences.xml
trytond/modules/authentication_totp/view/user_setup_totp_done_form.xml
trytond/modules/authentication_totp/view/user_setup_totp_show_form.xml
trytond/modules/authentication_totp/view/user_setup_totp_skipped_form.xml
trytonlq_authentication_totp-5.6.0.dist-info/DESCRIPTION.rst
trytonlq_authentication_totp-5.6.0.dist-info/METADATA
trytonlq_authentication_totp-5.6.0.dist-info/RECORD
trytonlq_authentication_totp-5.6.0.dist-info/WHEEL
trytonlq_authentication_totp-5.6.0.dist-info/entry_points.txt
trytonlq_authentication_totp-5.6.0.dist-info/metadata.json
trytonlq_authentication_totp-5.6.0.dist-info/top_level.txt
